{
	"url": "https://github.com/MehediH/Tweeten/releases/download/4.2.2/tweeten-darwin-x64.zip",
	"version": "4.2.2",
	"message": "Tweeten 4.2.2 is now out with some enhancements",
	"new": [
		"You can now support Tweeten via Patreon"
	],
	"fixes": [
		"Fixed an issue where GIF Search would remove the tweet that you are replying to after adding a new GIF",
		"Fixed an issue where the like/favorite icon's placement would be visually incorrect",
		"Fixed an issue where the columns on modals wouldn't take up the full space"
	]
}
